pytest_aiohutils/__init__.py
pytest_aiohutils-0.22.5.dist-info/WHEEL
pytest_aiohutils-0.22.5.dist-info/entry_points.txt
pytest_aiohutils-0.22.5.dist-info/METADATA
pytest_aiohutils-0.22.5.dist-info/RECORD
