Metadata-Version: 2.3
Name: pytest-aiohutils
Version: 0.22.5
Summary: Pytest plugin providing fixtures and configuration for aiohutils projects (offline, record, cleanup modes).
Author: 5j9
Author-email: 5j9 <5j9@users.noreply.github.com>
License: GNU General Public License v3 (GPLv3)
Classifier: License :: OSI Approved :: GNU General Public License v3 (GPLv3)
Classifier: Programming Language :: Python :: 3.10
Requires-Dist: aiohutils
Requires-Dist: pytest
Requires-Dist: pytest-asyncio
Requires-Dist: pydantic
Requires-Python: >=3.12
Project-URL: Homepage, https://github.com/5j9/pytest-aiohutils
